{"Argentina": 0.2175, "Spain": 0.2045, "France": 0.1803, "England": 0.0925, "Brazil": 0.0367, "Portugal": 0.0315, "Colombia": 0.031, "Morocco": 0.0242, "Mexico": 0.0227, "Belgium": 0.0216, "Switzerland": 0.0196, "Norway": 0.0186, "Netherlands": 0.018, "Japan": 0.0119, "Germany": 0.0093, "Ecuador": 0.0073, "United States": 0.0069, "Croatia": 0.0064, "Paraguay": 0.0049, "Turkey": 0.0043, "Egypt": 0.0039, "Uruguay": 0.0033, "Iran": 0.0032, "Senegal": 0.0031, "Canada": 0.0029, "South Korea": 0.0025, "Ivory Coast": 0.0024, "Australia": 0.0021, "Austria": 0.002, "Algeria": 0.0011, "Sweden": 0.001, "DR Congo": 0.0009, "Scotland": 0.0008, "Panama": 0.0005, "Jordan": 0.0002, "South Africa": 0.0001, "Cape Verde": 0.0001, "New Zealand": 0.0001, "Bosnia and Herzegovina": 0.0001, "Saudi Arabia": 0.0, "Ghana": 0.0, "Cura\u00e7ao": 0.0, "Czech Republic": 0.0, "Uzbekistan": 0.0, "Qatar": 0.0, "Haiti": 0.0, "Tunisia": 0.0, "Iraq": 0.0}