[
  {
    "home": "Argentina",
    "away": "Austria",
    "date": "2026-06-22",
    "ph": 0.6428,
    "pd": 0.2266,
    "pa": 0.1306
  },
  {
    "home": "France",
    "away": "Iraq",
    "date": "2026-06-22",
    "ph": 0.8939,
    "pd": 0.0765,
    "pa": 0.0297
  },
  {
    "home": "Norway",
    "away": "Senegal",
    "date": "2026-06-23",
    "ph": 0.4289,
    "pd": 0.2733,
    "pa": 0.2977
  },
  {
    "home": "Jordan",
    "away": "Algeria",
    "date": "2026-06-23",
    "ph": 0.1585,
    "pd": 0.2311,
    "pa": 0.6104
  },
  {
    "home": "Portugal",
    "away": "Uzbekistan",
    "date": "2026-06-23",
    "ph": 0.8019,
    "pd": 0.1372,
    "pa": 0.0609
  },
  {
    "home": "England",
    "away": "Ghana",
    "date": "2026-06-23",
    "ph": 0.7872,
    "pd": 0.1466,
    "pa": 0.0662
  },
  {
    "home": "Panama",
    "away": "Croatia",
    "date": "2026-06-23",
    "ph": 0.1418,
    "pd": 0.2383,
    "pa": 0.6199
  },
  {
    "home": "Colombia",
    "away": "DR Congo",
    "date": "2026-06-24",
    "ph": 0.6315,
    "pd": 0.2327,
    "pa": 0.1359
  },
  {
    "home": "Bosnia & Herzegovina",
    "away": "Qatar",
    "date": "2026-06-24",
    "ph": 0.6672,
    "pd": 0.1957,
    "pa": 0.137
  },
  {
    "home": "Switzerland",
    "away": "Canada",
    "date": "2026-06-24",
    "ph": 0.388,
    "pd": 0.3119,
    "pa": 0.3
  },
  {
    "home": "Scotland",
    "away": "Brazil",
    "date": "2026-06-24",
    "ph": 0.1215,
    "pd": 0.1861,
    "pa": 0.6924
  },
  {
    "home": "Morocco",
    "away": "Haiti",
    "date": "2026-06-24",
    "ph": 0.804,
    "pd": 0.137,
    "pa": 0.059
  },
  {
    "home": "Czech Republic",
    "away": "Mexico",
    "date": "2026-06-25",
    "ph": 0.2562,
    "pd": 0.2526,
    "pa": 0.4913
  },
  {
    "home": "South Africa",
    "away": "South Korea",
    "date": "2026-06-25",
    "ph": 0.1682,
    "pd": 0.2442,
    "pa": 0.5876
  },
  {
    "home": "Curaçao",
    "away": "Ivory Coast",
    "date": "2026-06-25",
    "ph": 0.0494,
    "pd": 0.1116,
    "pa": 0.839
  },
  {
    "home": "Ecuador",
    "away": "Germany",
    "date": "2026-06-25",
    "ph": 0.2631,
    "pd": 0.2506,
    "pa": 0.4862
  },
  {
    "home": "Japan",
    "away": "Sweden",
    "date": "2026-06-25",
    "ph": 0.4928,
    "pd": 0.2762,
    "pa": 0.2311
  },
  {
    "home": "Tunisia",
    "away": "Netherlands",
    "date": "2026-06-25",
    "ph": 0.0464,
    "pd": 0.1109,
    "pa": 0.8427
  },
  {
    "home": "Paraguay",
    "away": "Australia",
    "date": "2026-06-26",
    "ph": 0.3332,
    "pd": 0.4207,
    "pa": 0.246
  },
  {
    "home": "Turkey",
    "away": "United States",
    "date": "2026-06-26",
    "ph": 0.2735,
    "pd": 0.2362,
    "pa": 0.4902
  },
  {
    "home": "Norway",
    "away": "France",
    "date": "2026-06-26",
    "ph": 0.2203,
    "pd": 0.2498,
    "pa": 0.5299
  },
  {
    "home": "Senegal",
    "away": "Iraq",
    "date": "2026-06-26",
    "ph": 0.7285,
    "pd": 0.1789,
    "pa": 0.0925
  },
  {
    "home": "Cape Verde",
    "away": "Saudi Arabia",
    "date": "2026-06-27",
    "ph": 0.4025,
    "pd": 0.2614,
    "pa": 0.3362
  },
  {
    "home": "Uruguay",
    "away": "Spain",
    "date": "2026-06-27",
    "ph": 0.1485,
    "pd": 0.2241,
    "pa": 0.6274
  },
  {
    "home": "New Zealand",
    "away": "Belgium",
    "date": "2026-06-27",
    "ph": 0.0735,
    "pd": 0.145,
    "pa": 0.7815
  },
  {
    "home": "Egypt",
    "away": "Iran",
    "date": "2026-06-27",
    "ph": 0.391,
    "pd": 0.3454,
    "pa": 0.2636
  },
  {
    "home": "Croatia",
    "away": "Ghana",
    "date": "2026-06-27",
    "ph": 0.5834,
    "pd": 0.2512,
    "pa": 0.1654
  },
  {
    "home": "Panama",
    "away": "England",
    "date": "2026-06-27",
    "ph": 0.0846,
    "pd": 0.1431,
    "pa": 0.7723
  },
  {
    "home": "Colombia",
    "away": "Portugal",
    "date": "2026-06-27",
    "ph": 0.2636,
    "pd": 0.2744,
    "pa": 0.462
  },
  {
    "home": "DR Congo",
    "away": "Uzbekistan",
    "date": "2026-06-27",
    "ph": 0.4572,
    "pd": 0.2625,
    "pa": 0.2803
  },
  {
    "home": "Algeria",
    "away": "Austria",
    "date": "2026-06-28",
    "ph": 0.3105,
    "pd": 0.3099,
    "pa": 0.3796
  },
  {
    "home": "Jordan",
    "away": "Argentina",
    "date": "2026-06-28",
    "ph": 0.068,
    "pd": 0.1356,
    "pa": 0.7964
  }
]